Workbook

Sheet Tracker
A1: Control | B1: Safeguard | C1: Safeguard Title | D1: Req ID | E1: Requirement | F1: Group | G1: Scope | H1: Check | I1: Not Retroactive | J1: Status | K1: Owner | L1: PR / Ticket | M1: Raised | N1: Verified | O1: Notes
A2: Control 01 — Inventory and Control of Enterprise Assets | B2: 1.1 | C2: Establish and Maintain Detailed Enterprise Asset Inventory | D2: 1.1#1 | E2: Cloud Asset Inventory feed configured at organization scope | F2: CLI + human review | G2: org | H2: V1 | J2: Not started
A3: Control 01 — Inventory and Control of Enterprise Assets | B3: 1.1 | C3: Establish and Maintain Detailed Enterprise Asset Inventory | D3: 1.1#2 | E3: Feed exports to BigQuery or Cloud Storage on a scheduled basis | F3: CLI + human review | G3: org | H3: V2 | J3: Not started
A4: Control 01 — Inventory and Control of Enterprise Assets | B4: 1.1 | C4: Establish and Maintain Detailed Enterprise Asset Inventory | D4: 1.1#3 | E4: All projects enumerated, including those created flat under the org node | F4: CLI + human review | G4: org | H4: V3 | J4: Not started
A5: Control 01 — Inventory and Control of Enterprise Assets | B5: 1.1 | C5: Establish and Maintain Detailed Enterprise Asset Inventory | D5: 1.1#4 | E5: Inventory covers Compute Engine, GKE, Cloud SQL, Cloud Run, Cloud Functions, App Engine, Cloud Storage | F5: CLI + human review | G5: org | H5: V4 | J5: Not started
A6: Control 01 — Inventory and Control of Enterprise Assets | B6: 1.1 | C6: Establish and Maintain Detailed Enterprise Asset Inventory | D6: 1.1#5 | E6: Required labels enforced (owner, environment, cost centre, data classification) | F6: Automated | G6: org | H6: V5 | J6: Not started
A7: Control 01 — Inventory and Control of Enterprise Assets | B7: 1.1 | C7: Establish and Maintain Detailed Enterprise Asset Inventory | D7: 1.1#6 | E7: Shared VPC host and service project relationships mapped | F7: CLI + human review | G7: project | H7: V6 | J7: Not started
A8: Control 01 — Inventory and Control of Enterprise Assets | B8: 1.1 | C8: Establish and Maintain Detailed Enterprise Asset Inventory | D8: 1.1#7 | E8: Inventory reviewed and recertified at least every six months | F8: GCP manual | J8: Not started
A9: Control 01 — Inventory and Control of Enterprise Assets | B9: 1.2 | C9: Address Unauthorized Assets | D9: 1.2#1 | E9: Documented process for resources found without an owner or approval | F9: GCP manual | J9: Not started
A10: Control 01 — Inventory and Control of Enterprise Assets | B10: 1.2 | C10: Address Unauthorized Assets | D10: 1.2#2 | E10: Projects with no billing account or in DELETE_REQUESTED state dispositioned | F10: CLI + human review | G10: project | H10: V7 | J10: Not started
A11: Control 01 — Inventory and Control of Enterprise Assets | B11: 1.2 | C11: Address Unauthorized Assets | D11: 1.2#3 | E11: Orphaned resources reconciled (unattached disks, unused static IPs, idle forwarding rules) | F11: Automated | G11: org | H11: V8 | J11: Not started
A12: Control 01 — Inventory and Control of Enterprise Assets | B12: 1.2 | C12: Address Unauthorized Assets | D12: 1.2#4 | E12: Unlabelled or unattributable resources escalated within a defined window | F12: GCP manual | J12: Not started
A13: Control 01 — Inventory and Control of Enterprise Assets | B13: 1.2 | C13: Address Unauthorized Assets | D13: 1.2#5 | E13: Remediation actions recorded (removed, quarantined, or formally accepted) | F13: GCP manual | J13: Not started
A14: Control 02 — Inventory and Control of Software Assets | B14: 2.1 | C14: Establish and Maintain a Software Inventory | D14: 2.1#1 | E14: VM Manager OS inventory enabled; OS Config agent present on all Compute Engine instances | F14: CLI + human review | G14: project | H14: V9 | J14: Not started
A15: Control 02 — Inventory and Control of Software Assets | B15: 2.1 | C15: Establish and Maintain a Software Inventory | D15: 2.1#2 | E15: Custom image and image family catalogue maintained with build provenance | F15: CLI + human review | G15: project | H15: V10 | J15: Not started
A16: Control 02 — Inventory and Control of Software Assets | B16: 2.1 | C16: Establish and Maintain a Software Inventory | D16: 2.1#3 | E16: Artifact Registry / Container Registry image inventory captured | F16: CLI + human review | G16: project | H16: V11 | J16: Not started
A17: Control 02 — Inventory and Control of Software Assets | B17: 2.1 | C17: Establish and Maintain a Software Inventory | D17: 2.1#4 | E17: GKE cluster and node pool versions recorded | F17: CLI + human review | G17: project | H17: V12 | J17: Not started
A18: Control 02 — Inventory and Control of Software Assets | B18: 2.1 | C18: Establish and Maintain a Software Inventory | D18: 2.1#5 | E18: Cloud Functions, Cloud Run, and App Engine runtime versions recorded | F18: CLI + human review | G18: project | H18: V13 | J18: Not started
A19: Control 02 — Inventory and Control of Software Assets | B19: 2.1 | C19: Establish and Maintain a Software Inventory | D19: 2.1#6 | E19: Cloud SQL engine and version recorded per instance | F19: CLI + human review | G19: project | H19: V14 | J19: Not started
A20: Control 02 — Inventory and Control of Software Assets | B20: 2.1 | C20: Establish and Maintain a Software Inventory | D20: 2.1#7 | E20: Inventory refreshed automatically, not by manual survey | F20: Process & people | J20: Not started
A21: Control 02 — Inventory and Control of Software Assets | B21: 2.2 | C21: Ensure Authorized Software is Currently Supported | D21: 2.2#1 | E21: No instances running end-of-life guest OS (CentOS 7, Debian 9/10, out-of-window Ubuntu) | F21: Automated | G21: org | H21: V15 | J21: Not started
A22: Control 02 — Inventory and Control of Software Assets | B22: 2.2 | C22: Ensure Authorized Software is Currently Supported | D22: 2.2#2 | E22: No GKE clusters on versions past end-of-life; all enrolled in a release channel | F22: Automated | G22: project | H22: V16 | J22: Not started
A23: Control 02 — Inventory and Control of Software Assets | B23: 2.2 | C23: Ensure Authorized Software is Currently Supported | D23: 2.2#3 | E23: No Cloud Functions or App Engine services on decommissioned runtimes | F23: CLI + human review | G23: project | H23: V17 | J23: Not started
A24: Control 02 — Inventory and Control of Software Assets | B24: 2.2 | C24: Ensure Authorized Software is Currently Supported | D24: 2.2#4 | E24: No Cloud SQL instances on unsupported database versions | F24: CLI + human review | G24: project | H24: V18 | J24: Not started
A25: Control 02 — Inventory and Control of Software Assets | B25: 2.2 | C25: Ensure Authorized Software is Currently Supported | D25: 2.2#5 | E25: Deprecated custom images not referenced by any instance template or MIG | F25: CLI + human review | G25: project | H25: V19 | J25: Not started
A26: Control 02 — Inventory and Control of Software Assets | B26: 2.2 | C26: Ensure Authorized Software is Currently Supported | D26: 2.2#6 | E26: Exception register for unsupported software with documented compensating controls | F26: Process & people | J26: Not started
A27: Control 02 — Inventory and Control of Software Assets | B27: 2.3 | C27: Address Unauthorized Software | D27: 2.3#1 | E27: Documented process for removing unapproved software from the environment | F27: Process & people | J27: Not started
A28: Control 02 — Inventory and Control of Software Assets | B28: 2.3 | C28: Address Unauthorized Software | D28: 2.3#2 | E28: Marketplace deployment restricted to approved solutions | F28: Process & people | J28: Not started
A29: Control 02 — Inventory and Control of Software Assets | B29: 2.3 | C29: Address Unauthorized Software | D29: 2.3#3 | E29: Container images sourced only from approved registries | F29: CLI + human review | G29: project | H29: V20 | J29: Not started
A30: Control 02 — Inventory and Control of Software Assets | B30: 2.3 | C30: Address Unauthorized Software | D30: 2.3#4 | E30: Binary Authorization policy in place for GKE / Cloud Run (or a documented equivalent gate) | F30: CLI + human review | G30: project | H30: V21 | J30: Not started
A31: Control 02 — Inventory and Control of Software Assets | B31: 2.3 | C31: Address Unauthorized Software | D31: 2.3#5 | E31: workloads already running unattested identified and rolled | F31: CLI + human review | G31: project | H31: V22 | I31: Yes | J31: Not started
A32: Control 02 — Inventory and Control of Software Assets | B32: 2.3 | C32: Address Unauthorized Software | D32: 2.3#6 | E32: Findings tracked to closure with a defined remediation window | F32: Process & people | J32: Not started
A33: Control 03 — Data Protection | B33: 3.1 | C33: Establish and Maintain a Data Management Process | D33: 3.1#1 | E33: Written data management process covering sensitivity, ownership, handling, retention, disposal | F33: Process & people | J33: Not started
A34: Control 03 — Data Protection | B34: 3.1 | C34: Establish and Maintain a Data Management Process | D34: 3.1#2 | E34: Process references GCP storage services in use | F34: Process & people | J34: Not started
A35: Control 03 — Data Protection | B35: 3.1 | C35: Establish and Maintain a Data Management Process | D35: 3.1#3 | E35: Data residency requirements defined and mapped to regions | F35: CLI + human review | G35: org | H35: V23 | J35: Not started
A36: Control 03 — Data Protection | B36: 3.1 | C36: Establish and Maintain a Data Management Process | D36: 3.1#4 | E36: Reviewed annually with review date recorded | F36: Process & people | J36: Not started
A37: Control 03 — Data Protection | B37: 3.2 | C37: Establish and Maintain a Data Inventory | D37: 3.2#1 | E37: Sensitive Data Protection (Cloud DLP) discovery configured across Cloud Storage and BigQuery | F37: CLI + human review | G37: project | H37: V24 | J37: Not started
A38: Control 03 — Data Protection | B38: 3.2 | C38: Establish and Maintain a Data Inventory | D38: 3.2#2 | E38: Cloud SQL and other data stores included in the inventory | F38: GCP manual | J38: Not started
A39: Control 03 — Data Protection | B39: 3.2 | C39: Establish and Maintain a Data Inventory | D39: 3.2#3 | E39: Sensitivity classification recorded as resource labels or in a central register | F39: Automated | G39: org | H39: V25 | J39: Not started
A40: Control 03 — Data Protection | B40: 3.2 | C40: Establish and Maintain a Data Inventory | D40: 3.2#4 | E40: Data location recorded per store for residency verification | F40: CLI + human review | G40: org | H40: V26 | J40: Not started
A41: Control 03 — Data Protection | B41: 3.2 | C41: Establish and Maintain a Data Inventory | D41: 3.2#5 | E41: Inventory refreshed on a defined schedule | F41: GCP manual | J41: Not started
A42: Control 03 — Data Protection | B42: 3.3 | C42: Configure Data Access Control Lists | D42: 3.3#1 | E42: No Cloud Storage buckets granting allUsers or allAuthenticatedUsers | F42: Automated | G42: org | H42: V27 | J42: Not started
A43: Control 03 — Data Protection | B43: 3.3 | C43: Configure Data Access Control Lists | D43: 3.3#2 | E43: constraints/storage.publicAccessPrevention enforced at org level | F43: CLI + human review | G43: org | H43: V28 | J43: Not started
A44: Control 03 — Data Protection | B44: 3.3 | C44: Configure Data Access Control Lists | D44: 3.3#3 | E44: all currently public buckets and datasets found and remediated | F44: Automated | G44: org | H44: V29 | I44: Yes | J44: Not started
A45: Control 03 — Data Protection | B45: 3.3 | C45: Configure Data Access Control Lists | D45: 3.3#4 | E45: all buckets migrated off legacy per-object ACLs | F45: Automated | G45: project | H45: V30 | I45: Yes | J45: Not started
A46: Control 03 — Data Protection | B46: 3.3 | C46: Configure Data Access Control Lists | D46: 3.3#5 | E46: all pre-existing external-domain IAM grants reviewed and removed | F46: Automated | G46: org | H46: V31 | I46: Yes | J46: Not started
A47: Control 03 — Data Protection | B47: 3.3 | C47: Configure Data Access Control Lists | D47: 3.3#6 | E47: constraints/storage.uniformBucketLevelAccess enforced; legacy object ACLs retired | F47: CLI + human review | G47: org | H47: V32 | J47: Not started
A48: Control 03 — Data Protection | B48: 3.3 | C48: Configure Data Access Control Lists | D48: 3.3#7 | E48: No BigQuery datasets shared to allUsers or allAuthenticatedUsers | F48: Automated | G48: org | H48: V33 | J48: Not started
A49: Control 03 — Data Protection | B49: 3.3 | C49: Configure Data Access Control Lists | D49: 3.3#8 | E49: Access granted via groups and predefined/custom roles, not basic roles | F49: Automated | G49: org | H49: V34 | J49: Not started
A50: Control 03 — Data Protection | B50: 3.3 | C50: Configure Data Access Control Lists | D50: 3.3#9 | E50: constraints/iam.allowedPolicyMemberDomains enforced at org level | F50: CLI + human review | G50: org | H50: V35 | J50: Not started
A51: Control 03 — Data Protection | B51: 3.3 | C51: Configure Data Access Control Lists | D51: 3.3#10 | E51: VPC Service Controls perimeters around projects holding regulated data | F51: CLI + human review | G51: org | H51: V36 | J51: Not started
A52: Control 03 — Data Protection | B52: 3.3 | C52: Configure Data Access Control Lists | D52: 3.3#11 | E52: Access reviewed on a defined cadence with evidence retained | F52: Process & people | J52: Not started
A53: Control 03 — Data Protection | B53: 3.4 | C53: Enforce Data Retention | D53: 3.4#1 | E53: Retention periods defined per data class and documented | F53: Process & people | J53: Not started
A54: Control 03 — Data Protection | B54: 3.4 | C54: Enforce Data Retention | D54: 3.4#2 | E54: Object Lifecycle Management rules applied to Cloud Storage buckets | F54: Automated | G54: project | H54: V37 | J54: Not started
A55: Control 03 — Data Protection | B55: 3.4 | C55: Enforce Data Retention | D55: 3.4#3 | E55: BigQuery default table and partition expiration configured on datasets | F55: Automated | G55: project | H55: V38 | J55: Not started
A56: Control 03 — Data Protection | B56: 3.4 | C56: Enforce Data Retention | D56: 3.4#4 | E56: Cloud SQL backup retention windows set to the defined period | F56: CLI + human review | G56: project | H56: V39 | J56: Not started
A57: Control 03 — Data Protection | B57: 3.4 | C57: Enforce Data Retention | D57: 3.4#5 | E57: Log bucket retention set explicitly (not left at the _Default 30 days) | F57: CLI + human review | G57: org | H57: V40 | J57: Not started
A58: Control 03 — Data Protection | B58: 3.4 | C58: Enforce Data Retention | D58: 3.4#6 | E58: Buckets and datasets with no retention rule identified and remediated | F58: CLI + human review | H58: V41 | J58: Not started
A59: Control 03 — Data Protection | B59: 3.5 | C59: Securely Dispose of Data | D59: 3.5#1 | E59: Documented disposal process for each storage service in use | F59: Process & people | J59: Not started
A60: Control 03 — Data Protection | B60: 3.5 | C60: Securely Dispose of Data | D60: 3.5#2 | E60: Cloud Storage soft delete / versioning retention understood and accounted for in disposal | F60: CLI + human review | G60: project | H60: V42 | J60: Not started
A61: Control 03 — Data Protection | B61: 3.5 | C61: Securely Dispose of Data | D61: 3.5#3 | E61: CMEK key destruction procedure documented where crypto-shredding is the disposal method | F61: Process & people | J61: Not started
A62: Control 03 — Data Protection | B62: 3.5 | C62: Securely Dispose of Data | D62: 3.5#4 | E62: Snapshots, images, and backups included in disposal scope, not just live data | F62: Process & people | J62: Not started
A63: Control 03 — Data Protection | B63: 3.5 | C63: Securely Dispose of Data | D63: 3.5#5 | E63: Project deletion procedure includes verification that data is unrecoverable after the recovery window | F63: Process & people | J63: Not started
A64: Control 03 — Data Protection | B64: 3.5 | C64: Securely Dispose of Data | D64: 3.5#6 | E64: Disposal actions logged and evidenced | F64: Process & people | J64: Not started
A65: Control 04 — Secure Configuration of Enterprise Assets and Software | B65: 4.1 | C65: Establish and Maintain a Secure Configuration Process | D65: 4.1#1 | E65: Written secure configuration baseline for GCP resources | F65: Process & people | J65: Not started
A66: Control 04 — Secure Configuration of Enterprise Assets and Software | B66: 4.1 | C66: Establish and Maintain a Secure Configuration Process | D66: 4.1#2 | E66: Baseline enforced through Organization Policy constraints at the org node | F66: CLI + human review | G66: org | H66: V43 | J66: Not started
A67: Control 04 — Secure Configuration of Enterprise Assets and Software | B67: 4.1 | C67: Establish and Maintain a Secure Configuration Process | D67: 4.1#3 | E67: Constraints applied in dry-run first, violations triaged, then enforced | F67: Automated | G67: org | H67: V44 | J67: Not started
A68: Control 04 — Secure Configuration of Enterprise Assets and Software | B68: 4.1 | C68: Establish and Maintain a Secure Configuration Process | D68: 4.1#4 | E68: Infrastructure provisioned via infrastructure-as-code, not console clickops | F68: Process & people | J68: Not started
A69: Control 04 — Secure Configuration of Enterprise Assets and Software | B69: 4.1 | C69: Establish and Maintain a Secure Configuration Process | D69: 4.1#5 | E69: Drift detection running against declared state | F69: Process & people | J69: Not started
A70: Control 04 — Secure Configuration of Enterprise Assets and Software | B70: 4.1 | C70: Establish and Maintain a Secure Configuration Process | D70: 4.1#6 | E70: Security Command Center enabled at org scope for continuous posture assessment | F70: CLI + human review | G70: project | H70: V45 | J70: Not started
A71: Control 04 — Secure Configuration of Enterprise Assets and Software | B71: 4.1 | C71: Establish and Maintain a Secure Configuration Process | D71: 4.1#7 | E71: Baseline reviewed annually | F71: Process & people | J71: Not started
A72: Control 04 — Secure Configuration of Enterprise Assets and Software | B72: 4.2 | C72: Establish and Maintain a Secure Configuration Process for Network Infrastructure | D72: 4.2#1 | E72: Default VPC network removed from all projects | F72: Automated | G72: org | H72: V46 | J72: Not started
A73: Control 04 — Secure Configuration of Enterprise Assets and Software | B73: 4.2 | C73: Establish and Maintain a Secure Configuration Process for Network Infrastructure | D73: 4.2#2 | E73: constraints/compute.skipDefaultNetworkCreation enforced | F73: CLI + human review | G73: org | H73: V47 | J73: Not started
A74: Control 04 — Secure Configuration of Enterprise Assets and Software | B74: 4.2 | C74: Establish and Maintain a Secure Configuration Process for Network Infrastructure | D74: 4.2#3 | E74: default network deleted from every existing project | F74: CLI + human review | H74: V48 | I74: Yes | J74: Not started
A75: Control 04 — Secure Configuration of Enterprise Assets and Software | B75: 4.2 | C75: Establish and Maintain a Secure Configuration Process for Network Infrastructure | D75: 4.2#4 | E75: legacy and auto-mode VPCs identified and converted | F75: Automated | G75: project | H75: V49 | I75: Yes | J75: Not started
A76: Control 04 — Secure Configuration of Enterprise Assets and Software | B76: 4.2 | C76: Establish and Maintain a Secure Configuration Process for Network Infrastructure | D76: 4.2#5 | E76: Default firewall rules deleted (default-allow-ssh, default-allow-rdp, default-allow-icmp, default-allow-internal) | F76: Automated | G76: org | H76: V50 | J76: Not started
A77: Control 04 — Secure Configuration of Enterprise Assets and Software | B77: 4.2 | C77: Establish and Maintain a Secure Configuration Process for Network Infrastructure | D77: 4.2#6 | E77: Auto-mode VPCs converted to custom-mode; no legacy networks remain | F77: CLI + human review | H77: V51 | J77: Not started
A78: Control 04 — Secure Configuration of Enterprise Assets and Software | B78: 4.2 | C78: Establish and Maintain a Secure Configuration Process for Network Infrastructure | D78: 4.2#7 | E78: Documented network baseline covering subnets, routes, peering, and firewall standards | F78: Process & people | J78: Not started
A79: Control 04 — Secure Configuration of Enterprise Assets and Software | B79: 4.2 | C79: Establish and Maintain a Secure Configuration Process for Network Infrastructure | D79: 4.2#8 | E79: constraints/compute.restrictVpcPeering and Shared VPC constraints applied as required | F79: CLI + human review | G79: org | H79: V52 | J79: Not started
A80: Control 04 — Secure Configuration of Enterprise Assets and Software | B80: 4.2 | C80: Establish and Maintain a Secure Configuration Process for Network Infrastructure | D80: 4.2#9 | E80: Firewall rules logging enabled on rules governing sensitive paths | F80: Automated | G80: org | H80: V53 | J80: Not started
A81: Control 04 — Secure Configuration of Enterprise Assets and Software | B81: 4.3 | C81: Configure Automatic Session Locking on Enterprise Assets | D81: 4.3#1 | E81: Google Cloud session length configured in Admin Console (reauthentication frequency set, not "never") | F81: GCP manual | J81: Not started
A82: Control 04 — Secure Configuration of Enterprise Assets and Software | B82: 4.3 | C82: Configure Automatic Session Locking on Enterprise Assets | D82: 4.3#2 | E82: Reauthentication policy applied to Google Cloud CLI and API access | F82: GCP manual | J82: Not started
A83: Control 04 — Secure Configuration of Enterprise Assets and Software | B83: 4.3 | C83: Configure Automatic Session Locking on Enterprise Assets | D83: 4.3#3 | E83: IAP session duration configured for IAP-protected resources | F83: CLI + human review | G83: project | H83: V54 | J83: Not started
A84: Control 04 — Secure Configuration of Enterprise Assets and Software | B84: 4.3 | C84: Configure Automatic Session Locking on Enterprise Assets | D84: 4.3#4 | E84: Shell idle timeout set in the baked VM image for interactive sessions | F84: GCP manual | J84: Not started
A85: Control 04 — Secure Configuration of Enterprise Assets and Software | B85: 4.4 | C85: Implement and Manage a Firewall on Servers | D85: 4.4#1 | E85: No firewall rules permitting 0.0.0.0/0 to TCP 22 or TCP 3389 | F85: Automated | G85: org | H85: V55 | J85: Not started
A86: Control 04 — Secure Configuration of Enterprise Assets and Software | B86: 4.4 | C86: Implement and Manage a Firewall on Servers | D86: 4.4#2 | E86: No firewall rules permitting 0.0.0.0/0 to database ports (3306, 5432, 1433, 27017, 6379) | F86: Automated | G86: org | H86: V56 | J86: Not started
A87: Control 04 — Secure Configuration of Enterprise Assets and Software | B87: 4.4 | C87: Implement and Manage a Firewall on Servers | D87: 4.4#3 | E87: Default-deny ingress posture with explicit allow rules | F87: CLI + human review | G87: project | H87: V57 | J87: Not started
A88: Control 04 — Secure Configuration of Enterprise Assets and Software | B88: 4.4 | C88: Implement and Manage a Firewall on Servers | D88: 4.4#4 | E88: Egress rules constrained rather than default allow-all | F88: CLI + human review | G88: project | H88: V58 | J88: Not started
A89: Control 04 — Secure Configuration of Enterprise Assets and Software | B89: 4.4 | C89: Implement and Manage a Firewall on Servers | D89: 4.4#5 | E89: Rules scoped by network tag or service account rather than broad IP ranges | F89: Automated | G89: org | H89: V59 | J89: Not started
A90: Control 04 — Secure Configuration of Enterprise Assets and Software | B90: 4.4 | C90: Implement and Manage a Firewall on Servers | D90: 4.4#6 | E90: Cloud SQL public IP disabled (constraints/sql.restrictPublicIp); authorized networks not 0.0.0.0/0 | F90: CLI + human review | G90: org | H90: V60 | J90: Not started
A91: Control 04 — Secure Configuration of Enterprise Assets and Software | B91: 4.4 | C91: Implement and Manage a Firewall on Servers | D91: 4.4#7 | E91: existing Cloud SQL instances with public IP remediated | F91: Automated | G91: org | H91: V61 | I91: Yes | J91: Not started
A92: Control 04 — Secure Configuration of Enterprise Assets and Software | B92: 4.4 | C92: Implement and Manage a Firewall on Servers | D92: 4.4#8 | E92: existing firewall rules exposing 22/3389/DB ports to 0.0.0.0/0 removed | F92: CLI + human review | H92: V62 | I92: Yes | J92: Not started
A93: Control 04 — Secure Configuration of Enterprise Assets and Software | B93: 4.4 | C93: Implement and Manage a Firewall on Servers | D93: 4.4#9 | E93: GKE control plane authorized networks configured; private clusters in use | F93: CLI + human review | G93: project | H93: V63 | J93: Not started
A94: Control 04 — Secure Configuration of Enterprise Assets and Software | B94: 4.4 | C94: Implement and Manage a Firewall on Servers | D94: 4.4#10 | E94: Cloud Armor policies applied to externally exposed load balancers | F94: Automated | G94: project | H94: V64 | J94: Not started
A95: Control 04 — Secure Configuration of Enterprise Assets and Software | B95: 4.6 | C95: Securely Manage Enterprise Assets and Software | D95: 4.6#1 | E95: OS Login enforced org-wide (constraints/compute.requireOsLogin); project-wide SSH keys retired | F95: CLI + human review | G95: org | H95: V65 | J95: Not started
A96: Control 04 — Secure Configuration of Enterprise Assets and Software | B96: 4.6 | C96: Securely Manage Enterprise Assets and Software | D96: 4.6#2 | E96: existing VMs without OS Login identified and remediated | F96: Automated | G96: org | H96: V66 | I96: Yes | J96: Not started
A97: Control 04 — Secure Configuration of Enterprise Assets and Software | B97: 4.6 | C97: Securely Manage Enterprise Assets and Software | D97: 4.6#3 | E97: project-wide SSH keys removed from every existing project | F97: Automated | G97: project | H97: V67 | I97: Yes | J97: Not started
A98: Control 04 — Secure Configuration of Enterprise Assets and Software | B98: 4.6 | C98: Securely Manage Enterprise Assets and Software | D98: 4.6#4 | E98: existing VMs with external IPs migrated behind IAP | F98: Automated | G98: org | H98: V68 | I98: Yes | J98: Not started
A99: Control 04 — Secure Configuration of Enterprise Assets and Software | B99: 4.6 | C99: Securely Manage Enterprise Assets and Software | D99: 4.6#5 | E99: existing non-Shielded VMs replaced (requires stop or rebuild) | F99: Automated | G99: org | H99: V69 | I99: Yes | J99: Not started
A100: Control 04 — Secure Configuration of Enterprise Assets and Software | B100: 4.6 | C100: Securely Manage Enterprise Assets and Software | D100: 4.6#6 | E100: Serial port access disabled (constraints/compute.disableSerialPortAccess) | F100: CLI + human review | G100: org | H100: V70 | J100: Not started
...

Sheet Summary
A1: How to use this tracker
A2: Every figure below is a formula over the Tracker tab. Update Status there; this recalculates.
A4: Overall
A5: Total requirements | B5: =COUNTA(Tracker!D2:D291) -> 290
A6: Not started | B6: =COUNTIF(Tracker!$J$2:$J$291,A6) -> 290 | C6: =IFERROR(B6/$B$5,0) -> 1
A7: In progress | B7: =COUNTIF(Tracker!$J$2:$J$291,A7) -> 0 | C7: =IFERROR(B7/$B$5,0) -> 0
A8: PR submitted | B8: =COUNTIF(Tracker!$J$2:$J$291,A8) -> 0 | C8: =IFERROR(B8/$B$5,0) -> 0
A9: Compliant | B9: =COUNTIF(Tracker!$J$2:$J$291,A9) -> 0 | C9: =IFERROR(B9/$B$5,0) -> 0
A10: N/A | B10: =COUNTIF(Tracker!$J$2:$J$291,A10) -> 0 | C10: =IFERROR(B10/$B$5,0) -> 0
A11: Compliant % | B11: =IFERROR(COUNTIF(Tracker!$J$2:$J$291,"Compliant")/$B$5,0) -> 0
A13: By verification group
A14: Group | B14: Total | C14: Compliant | D14: % done
A15: Automated | B15: =COUNTIF(Tracker!$F$2:$F$291,A15) -> 41 | C15: =COUNTIFS(Tracker!$F$2:$F$291,A15,Tracker!$J$2:$J$291,"Compliant") -> 0 | D15: =IFERROR(C15/B15,0) -> 0
A16: CLI + human review | B16: =COUNTIF(Tracker!$F$2:$F$291,A16) -> 147 | C16: =COUNTIFS(Tracker!$F$2:$F$291,A16,Tracker!$J$2:$J$291,"Compliant") -> 0 | D16: =IFERROR(C16/B16,0) -> 0
A17: GCP manual | B17: =COUNTIF(Tracker!$F$2:$F$291,A17) -> 30 | C17: =COUNTIFS(Tracker!$F$2:$F$291,A17,Tracker!$J$2:$J$291,"Compliant") -> 0 | D17: =IFERROR(C17/B17,0) -> 0
A18: Process & people | B18: =COUNTIF(Tracker!$F$2:$F$291,A18) -> 72 | C18: =COUNTIFS(Tracker!$F$2:$F$291,A18,Tracker!$J$2:$J$291,"Compliant") -> 0 | D18: =IFERROR(C18/B18,0) -> 0
A20: By scope
A21: Scope | B21: Total | C21: Compliant | D21: % done
A22: org | B22: =COUNTIF(Tracker!$G$2:$G$291,A22) -> 67 | C22: =COUNTIFS(Tracker!$G$2:$G$291,A22,Tracker!$J$2:$J$291,"Compliant") -> 0 | D22: =IFERROR(C22/B22,0) -> 0
A23: project | B23: =COUNTIF(Tracker!$G$2:$G$291,A23) -> 91 | C23: =COUNTIFS(Tracker!$G$2:$G$291,A23,Tracker!$J$2:$J$291,"Compliant") -> 0 | D23: =IFERROR(C23/B23,0) -> 0
A25: Where the work is sitting
A26: Outstanding with engineering | B26: =COUNTIF(Tracker!$J$2:$J$291,"Not started")+COUNTIF(Tracker!$J$2:$J$291,"In progress") -> 290
A27: Awaiting management approval | B27: =COUNTIF(Tracker!$J$2:$J$291,"PR submitted") -> 0
A28: Done | B28: =COUNTIF(Tracker!$J$2:$J$291,"Compliant") -> 0
A29: Not applicable | B29: =COUNTIF(Tracker!$J$2:$J$291,"N/A") -> 0
A30: A PR sitting unapproved is a management decision, not an engineering backlog item.
A32: By safeguard
A33: Safeguard | B33: Requirements | C33: Compliant | D33: Safeguard met?
A34: 1.1 | B34: =COUNTIF(Tracker!$B$2:$B$291,A34) -> 7 | C34: =COUNTIFS(Tracker!$B$2:$B$291,A34,Tracker!$J$2:$J$291,"Compliant") -> 0 | D34: =IF(B34=C34,"MET","not met") -> not met
A35: 1.2 | B35: =COUNTIF(Tracker!$B$2:$B$291,A35) -> 5 | C35: =COUNTIFS(Tracker!$B$2:$B$291,A35,Tracker!$J$2:$J$291,"Compliant") -> 0 | D35: =IF(B35=C35,"MET","not met") -> not met
A36: 2.1 | B36: =COUNTIF(Tracker!$B$2:$B$291,A36) -> 7 | C36: =COUNTIFS(Tracker!$B$2:$B$291,A36,Tracker!$J$2:$J$291,"Compliant") -> 0 | D36: =IF(B36=C36,"MET","not met") -> not met
A37: 2.2 | B37: =COUNTIF(Tracker!$B$2:$B$291,A37) -> 6 | C37: =COUNTIFS(Tracker!$B$2:$B$291,A37,Tracker!$J$2:$J$291,"Compliant") -> 0 | D37: =IF(B37=C37,"MET","not met") -> not met
A38: 2.3 | B38: =COUNTIF(Tracker!$B$2:$B$291,A38) -> 6 | C38: =COUNTIFS(Tracker!$B$2:$B$291,A38,Tracker!$J$2:$J$291,"Compliant") -> 0 | D38: =IF(B38=C38,"MET","not met") -> not met
A39: 3.1 | B39: =COUNTIF(Tracker!$B$2:$B$291,A39) -> 4 | C39: =COUNTIFS(Tracker!$B$2:$B$291,A39,Tracker!$J$2:$J$291,"Compliant") -> 0 | D39: =IF(B39=C39,"MET","not met") -> not met
A40: 3.2 | B40: =COUNTIF(Tracker!$B$2:$B$291,A40) -> 5 | C40: =COUNTIFS(Tracker!$B$2:$B$291,A40,Tracker!$J$2:$J$291,"Compliant") -> 0 | D40: =IF(B40=C40,"MET","not met") -> not met
A41: 3.3 | B41: =COUNTIF(Tracker!$B$2:$B$291,A41) -> 11 | C41: =COUNTIFS(Tracker!$B$2:$B$291,A41,Tracker!$J$2:$J$291,"Compliant") -> 0 | D41: =IF(B41=C41,"MET","not met") -> not met
A42: 3.4 | B42: =COUNTIF(Tracker!$B$2:$B$291,A42) -> 6 | C42: =COUNTIFS(Tracker!$B$2:$B$291,A42,Tracker!$J$2:$J$291,"Compliant") -> 0 | D42: =IF(B42=C42,"MET","not met") -> not met
A43: 3.5 | B43: =COUNTIF(Tracker!$B$2:$B$291,A43) -> 6 | C43: =COUNTIFS(Tracker!$B$2:$B$291,A43,Tracker!$J$2:$J$291,"Compliant") -> 0 | D43: =IF(B43=C43,"MET","not met") -> not met
A44: 4.1 | B44: =COUNTIF(Tracker!$B$2:$B$291,A44) -> 7 | C44: =COUNTIFS(Tracker!$B$2:$B$291,A44,Tracker!$J$2:$J$291,"Compliant") -> 0 | D44: =IF(B44=C44,"MET","not met") -> not met
A45: 4.2 | B45: =COUNTIF(Tracker!$B$2:$B$291,A45) -> 9 | C45: =COUNTIFS(Tracker!$B$2:$B$291,A45,Tracker!$J$2:$J$291,"Compliant") -> 0 | D45: =IF(B45=C45,"MET","not met") -> not met
... A77: 17.3 | B77: =COUNTIF(Tracker!$B$2:$B$291,A77) -> 6 | C77: =COUNTIFS(Tracker!$B$2:$B$291,A77,Tracker!$J$2:$J$291,"Compliant") -> 0 | D77: =IF(B77=C77,"MET","not met") -> not met
A79: Safeguards met | B79: =COUNTIF(D34:D77,"MET") -> 0
A80: A safeguard is met only when every one of its requirements is Compliant. No partial credit.

Sheet How to use
A4: Where to type | B4: Only the shaded columns on the Tracker tab: Status, Owner, PR / Ticket, Raised, Verified, Notes. Everything to their left is generated from the repository and will be overwritten if the tracker is regenerated.
A6: Status values | B6: Not started · In progress · PR submitted · Compliant · N/A
A7: Compliant | B7: Means verified in the live estate. Not 'merged', not 'applied' — verified. A merged PR nobody confirmed is still 'PR submitted'.
A8: PR submitted | B8: The fix is written and raised. The item is now waiting on management approval, not on engineering. Put the PR number in the PR / Ticket column and the date in Raised.
A9: N/A | B9: The product or service does not exist in this organization. Use sparingly — 'we never built a log bucket' is a failure, not an N/A.
A11: Group | B11: How the requirement gets checked:
A12: Automated | B12: audit-run.go runs it and scores pass/fail. 41 requirements.
A13: CLI + human review | B13: audit-run.go runs it and saves the output; a person judges the result. 147 requirements.
A14: GCP manual | B14: A GCP task with no CLI — Admin Console, image build, or a test to perform. 30 requirements.
A15: Process & people | B15: Answered by a conversation and a document, not a command. 72 requirements.
A17: Scope | B17: org = checked once for the whole organization. project = checked once per project.
A18: Check | B18: The V-number in docs/cis-ig1-cli-validation.md holding the command and its pass criteria.
... A21: Scope boundary | B21: These 290 requirements are the GCP-actionable half of IG1. Twelve IG1 safeguards — security awareness training, end-user devices, removable media — have no GCP surface, are not in this sheet, and are owned elsewhere. 100% here is not 100% IG1.
